myexe/__init__.py
myexe/launcher.py
myexe_package-0.1.0.dist-info/METADATA
myexe_package-0.1.0.dist-info/WHEEL
myexe_package-0.1.0.dist-info/entry_points.txt
myexe_package-0.1.0.dist-info/top_level.txt
myexe_package-0.1.0.dist-info/RECORD
