Metadata-Version: 2.4
Name: myexe-package
Version: 0.1.0
Summary: 一個透過 pip 安裝的單一 EXE 包
Classifier: Programming Language :: Python :: 3
Classifier: Operating System :: Microsoft :: Windows
Requires-Python: >=3.6
Dynamic: classifier
Dynamic: requires-python
Dynamic: summary
